evaporation/__init__.py
evaporation/cli.py
evaporation/evaporation.py
evaporation-2.0.1.dist-info/LICENSE
evaporation-2.0.1.dist-info/METADATA
evaporation-2.0.1.dist-info/WHEEL
evaporation-2.0.1.dist-info/entry_points.txt
evaporation-2.0.1.dist-info/top_level.txt
evaporation-2.0.1.dist-info/RECORD
