Metadata-Version: 2.1
Name: evaporation
Version: 2.0.1
Summary: Calculation of evaporation and transpiration
Home-page: https://github.com/openmeteo/evaporation
Author: Antonis Christofides
Author-email: antonis@antonischristofides.com
License: GNU General Public License v3
Keywords: evaporation
Classifier: Development Status :: 4 - Beta
Classifier: Intended Audience :: Developers
Classifier: License :: OSI Approved :: GNU General Public License v3 (GPLv3)
Classifier: Natural Language :: English
Classifier: Programming Language :: Python :: 3.7
Classifier: Programming Language :: Python :: 3.8
Classifier: Programming Language :: Python :: 3.9
License-File: LICENSE
Requires-Dist: Click >=7.0
Requires-Dist: iso8601
Requires-Dist: hspatial <5,>=3
